redexpect/__init__.py
redexpect/exceptions.py
redexpect/redexpect.py
redexpect-2.0.3.post3.dist-info/LICENSE
redexpect-2.0.3.post3.dist-info/METADATA
redexpect-2.0.3.post3.dist-info/WHEEL
redexpect-2.0.3.post3.dist-info/top_level.txt
redexpect-2.0.3.post3.dist-info/RECORD
